kovol_language_tools/__init__.py
kovol_language_tools/_version.py
kovol_language_tools/facts.py
kovol_language_tools/phonemics.py
kovol_language_tools/verbs.py
kovol_language_tools-0.0.12.dist-info/LICENSE
kovol_language_tools-0.0.12.dist-info/METADATA
kovol_language_tools-0.0.12.dist-info/WHEEL
kovol_language_tools-0.0.12.dist-info/top_level.txt
kovol_language_tools-0.0.12.dist-info/RECORD
